goldnlp/__init__.py
goldnlp/classifying.py
goldnlp/constants.py
goldnlp/crosslinking.py
goldnlp/events.py
goldnlp/extracting.py
goldnlp/ngramchunker.py
goldnlp/nlpdocument.py
goldnlp/quality_check.py
goldnlp/spacy_pipeline.py
goldnlp/spacy_utils.py
goldnlp/summarizing.py
goldnlp/timer.py
goldnlp/utils.py
goldnlp-0.0.2.dist-info/WHEEL
goldnlp-0.0.2.dist-info/METADATA
goldnlp-0.0.2.dist-info/RECORD
